hota/__init__.py
hota/html.py
hota/template/__init__.py
hota/template/custom.py
hota/template/dom.py
hota/template/element.py
hota/template/handler.py
hota/template/internal.py
hota/template/node.py
hota/template/text.py
hota/template/utils.py
hota/websocket.py
LICENSE
hota-0.1.0.dist-info/LICENSE
hota-0.1.0.dist-info/WHEEL
hota-0.1.0.dist-info/METADATA
hota-0.1.0.dist-info/RECORD
